pybayesprism/__init__.py
pybayesprism/compare.py
pybayesprism/extract.py
pybayesprism/gibbs.py
pybayesprism/joint_post.py
pybayesprism/main.py
pybayesprism/optim.py
pybayesprism/prism.py
pybayesprism/process_input.py
pybayesprism/references.py
pybayesprism/run.py
pybayesprism/theta_post.py
pybayesprism/txt/gencode.v22.broad.category.txt
pybayesprism/txt/genelist.hs.new.txt
pybayesprism/txt/genelist.mm.new.txt
pybayesprism-0.0.10.dist-info/LICENSE
pybayesprism-0.0.10.dist-info/METADATA
pybayesprism-0.0.10.dist-info/WHEEL
pybayesprism-0.0.10.dist-info/top_level.txt
pybayesprism-0.0.10.dist-info/RECORD
