Metadata-Version: 2.1
Name: pybayesprism
Version: 0.0.10
Summary: Python implementation of BayesPrism
Author-email: Zilu Wang <zw427@cornell.edu>
Project-URL: Homepage, https://github.com/ziluwang829/pyBayesPrism
Project-URL: Issues, https://github.com/ziluwang829/pyBayesPrism/issues
Classifier: Programming Language :: Python :: 3
Classifier: License :: OSI Approved :: MIT License
Classifier: Operating System :: OS Independent
Requires-Python: >=3.8
License-File: LICENSE
Requires-Dist: pandas
Requires-Dist: numpy
Requires-Dist: scipy
Requires-Dist: xarray
Requires-Dist: tqdm
